Metadata-Version: 2.1
Name: odoo12-addon-l10n-es-ticketbai-api
Version: 12.0.2.3.8
Summary: TicketBAI - API
Home-page: https://github.com/OCA/l10n-spain
Author: Binovo,Odoo Community Association (OCA)
Author-email: support@odoo-community.org
License: AGPL-3
Platform: UNKNOWN
Classifier: Programming Language :: Python
Classifier: Framework :: Odoo
Classifier: Framework :: Odoo :: 12.0
Classifier: License :: OSI Approved :: GNU Affero General Public License v3
Classifier: Development Status :: 4 - Beta
Requires-Python: >=3.5
Requires-Dist: cryptography <39
Requires-Dist: odoo <12.1dev,>=12.0a
Requires-Dist: pyOpenSSL
Requires-Dist: qrcode
Requires-Dist: requests-pkcs12
Requires-Dist: xmlsig
Requires-Dist: xmltodict
